<?xml version="1.0" encoding="utf-8" ?>
<dwsync>
<file name="1_comingsoon.png" server="www.thekortes.net//" local="129564674160976560" remote="129626716800000000" />
<file name="HM_logo.png" server="www.thekortes.net//" local="129562816180244587" remote="129602643600000000" />
<file name="horizdiv1.png" server="www.thekortes.net//" local="129564351776000566" remote="129626718000000000" />
<file name="horizdiv2.png" server="www.thekortes.net//" local="129564352596477494" remote="129626718000000000" />
<file name="horizdiv17.png" server="www.thekortes.net//" local="129564574378437504" remote="129602643600000000" />
<file name="horizdiv19.png" server="www.thekortes.net//" local="129564578516328128" remote="129602643600000000" />
<file name="mckiddos_png.png" server="www.thekortes.net//" local="129564624376762438" remote="129602643600000000" />
<file name="2_comingsoon.png" server="www.thekortes.net//" local="129564674893681840" remote="129602642400000000" />
<file name="arrow.png" server="www.thekortes.net//" local="129564640459492317" remote="129626716800000000" />
<file name="horizdiv15.png" server="www.thekortes.net//" local="129564500403911596" remote="129626718000000000" />
<file name="horizdiv16.png" server="www.thekortes.net//" local="129564506877851568" remote="129626718000000000" />
<file name="horizdiv18.png" server="www.thekortes.net//" local="129564576235078128" remote="129626718000000000" />
<file name="horizdiv19_inv.png" server="www.thekortes.net//" local="129564648442656256" remote="129626718000000000" />
<file name="mckiddos.jpg" server="www.thekortes.net//" local="129564622784541368" remote="129626718000000000" />
<file name="power_gr.png" server="www.thekortes.net//" local="129626759711385950" remote="129626767800000000" />
<file name="datablock.png" server="www.thekortes.net//" local="129578562401289056" remote="129602643000000000" />
<file name="power.png" server="www.thekortes.net//" local="129626759438120320" remote="129626767800000000" />
<file name="horiz_div.png" server="www.thekortes.net//" local="129578535840807899" remote="129602643600000000" />
<file name="Flash_Placeholder.png" server="www.thekortes.net//" local="129578943192432273" remote="129626718000000000" />
<file name="horiz_div2.png" server="www.thekortes.net//" local="129586082569592374" remote="129602643600000000" />
<file name="Flash_Placeholder2.png" server="www.thekortes.net//" local="129586085836679680" remote="129602643600000000" />
<file name="spacer.gif" server="www.thekortes.net//" local="129586124466467620" remote="129602643600000000" />
<file name="HM_logo250w.png" server="www.thekortes.net//" local="129590194186640624" remote="129602643600000000" />
<file name="horiz_div958w.png" server="www.thekortes.net//" local="129590200574742732" remote="129602643600000000" />
<file name="loading.gif" server="www.thekortes.net//" local="129593007527397868" remote="129626718000000000" />
<file name="x.png" server="www.thekortes.net//" local="129593007520347465" remote="129626718000000000" />
<file name="restore.png" server="www.thekortes.net//" local="129593007536188371" remote="129626718000000000" />
<file name="HM-Submit-A.png" server="www.thekortes.net//" local="129602586886484384" remote="129626718000000000" />
<file name="send.png" server="www.thekortes.net//" local="129602609461259987" remote="129602643600000000" />
<file name="badgeroster_pl.png" server="www.thekortes.net//" local="129579134926910078" remote="129626718000000000" />
<file name="HM-Submit-B.png" server="www.thekortes.net//" local="129602587817382028" remote="129626718000000000" />
<file name="horiz_div240.png" server="www.thekortes.net//" local="129590197930741504" remote="129626718000000000" />
<file name="mckiddos_png.jpg" server="www.thekortes.net//" local="129593067024347021" remote="129626718000000000" />
<file name="thiief.png" server="www.thekortes.net//" local="129570704691815753" remote="129626718000000000" />
<file name="white_center_1000.png" server="www.thekortes.net//" local="129586938207332019" remote="129626718000000000" />
<file name="facebook_16.png" server="www.thekortes.net//" local="129626724314411359" remote="129626767800000000" />
<file name="twitter_16.png" server="www.thekortes.net//" local="129626724941877248" remote="129626767800000000" />
<file name="youtube_16.png" server="www.thekortes.net//" local="129626724988859935" remote="129626767800000000" />
<file name="AddThis_16.png" server="www.thekortes.net//" local="129626725031882396" remote="129626767800000000" />
</dwsync>